.gitignore
LICENSE.md
MANIFEST.in
README.rst
setup.py
docs/Makefile
docs/README.rst
docs/make_html.sh
docs/requirements-doc.txt
docs/source/conf.py
docs/source/index.rst
docs/source/_static/placeholder.txt
docs/source/_templates/placeholder.txt
docs/source/_templates/autosummary/class.rst
docs/source/_templates/autosummary/module.rst
src/libgs_ops/__init__.py
src/libgs_ops/console_scripts.py
src/libgs_ops/propagator.py
src/libgs_ops/rpc.py
src/libgs_ops/scheduling.py
src/libgs_ops.egg-info/PKG-INFO
src/libgs_ops.egg-info/SOURCES.txt
src/libgs_ops.egg-info/dependency_links.txt
src/libgs_ops.egg-info/entry_points.txt
src/libgs_ops.egg-info/not-zip-safe
src/libgs_ops.egg-info/requires.txt
src/libgs_ops.egg-info/top_level.txt
tests/test_propagator.py
tests/test_scheduling.py